{
  "signed": false,
  "minimal_only": true,
  "num_vertices": 1640,
  "num_edges": 305713,
  "greedy_solution": {
    "size": 301,
    "vertex_ids": [
      600,
      605,
      6,
      73,
      22,
      25,
      27,
      29,
      30,
      31,
      32,
      33,
      41,
      43,
      45,
      47,
      49,
      51,
      54,
      86,
      105,
      197,
      1354,
      102,
      1235,
      12,
      11,
      725,
      78,
      79,
      1454,
      1462,
      744,
      1198,
      1537,
      1548,
      1552,
      1556,
      834,
      1341,
      62,
      779,
      782,
      576,
      788,
      792,
      129,
      1413,
      158,
      160,
      161,
      162,
      163,
      164,
      165,
      166,
      170,
      212,
      254,
      258,
      1434,
      1440,
      1447,
      271,
      120,
      1242,
      1248,
      1255,
      508,
      1079,
      284,
      290,
      294,
      298,
      323,
      313,
      141,
      334,
      337,
      339,
      341,
      344,
      349,
      554,
      560,
      569,
      355,
      358,
      360,
      621,
      626,
      365,
      367,
      368,
      369,
      370,
      371,
      372,
      1401,
      374,
      190,
      405,
      403,
      401,
      417,
      425,
      433,
      440,
      411,
      449,
      1041,
      1045,
      1048,
      458,
      1165,
      1169,
      973,
      983,
      1567,
      1571,
      485,
      488,
      183,
      495,
      498,
      503,
      514,
      380,
      383,
      386,
      20,
      520,
      1391,
      917,
      613,
      618,
      632,
      1297,
      756,
      640,
      539,
      467,
      541,
      542,
      543,
      544,
      549,
      585,
      590,
      593,
      611,
      645,
      650,
      654,
      656,
      661,
      666,
      675,
      96,
      481,
      685,
      399,
      1345,
      1347,
      1496,
      1503,
      1509,
      855,
      865,
      881,
      694,
      1594,
      1473,
      708,
      711,
      714,
      718,
      723,
      730,
      733,
      734,
      735,
      736,
      1321,
      740,
      754,
      751,
      761,
      762,
      763,
      764,
      1151,
      1146,
      769,
      771,
      773,
      775,
      777,
      786,
      797,
      801,
      804,
      1003,
      810,
      811,
      812,
      813,
      829,
      1517,
      1521,
      1262,
      1263,
      958,
      959,
      1161,
      963,
      962,
      961,
      1621,
      1176,
      1184,
      999,
      995,
      104,
      1011,
      1026,
      154,
      1029,
      1030,
      1032,
      1037,
      847,
      231,
      177,
      1067,
      1116,
      532,
      535,
      536,
      537,
      1127,
      1615,
      1626,
      1132,
      1144,
      818,
      823,
      1218,
      1223,
      1226,
      1228,
      1230,
      1231,
      1232,
      1374,
      1378,
      1278,
      1281,
      1285,
      1021,
      915,
      1299,
      1300,
      1301,
      248,
      249,
      1137,
      1268,
      1271,
      1330,
      1331,
      1332,
      1094,
      1304,
      1351,
      1633,
      941,
      1366,
      1373,
      1381,
      1478,
      1477,
      1431,
      1481,
      1484,
      1489,
      378,
      1514,
      1494,
      1527,
      1577,
      36,
      39,
      1587,
      1588,
      1589,
      1590,
      1592,
      477,
      1607,
      1183
    ],
    "colors": [
      194,
      195,
      2,
      45,
      12,
      13,
      14,
      15,
      16,
      17,
      18,
      19,
      26,
      27,
      28,
      29,
      30,
      31,
      32,
      53,
      64,
      92,
      424,
      58,
      372,
      6,
      5,
      227,
      49,
      50,
      440,
      441,
      235,
      359,
      463,
      464,
      465,
      466,
      267,
      419,
      40,
      251,
      252,
      188,
      254,
      255,
      66,
      434,
      72,
      73,
      74,
      75,
      83,
      84,
      85,
      86,
      87,
      93,
      100,
      101,
      437,
      438,
      439,
      106,
      65,
      374,
      375,
      376,
      168,
      328,
      107,
      108,
      109,
      110,
      113,
      112,
      67,
      114,
      115,
      116,
      117,
      118,
      119,
      185,
      186,
      187,
      120,
      121,
      122,
      199,
      200,
      126,
      129,
      130,
      131,
      132,
      133,
      134,
      433,
      136,
      91,
      149,
      148,
      147,
      151,
      152,
      153,
      154,
      150,
      155,
      305,
      306,
      307,
      156,
      353,
      354,
      287,
      288,
      468,
      469,
      162,
      163,
      90,
      165,
      166,
      167,
      169,
      139,
      140,
      141,
      11,
      170,
      432,
      274,
      197,
      198,
      201,
      391,
      238,
      202,
      178,
      157,
      180,
      181,
      182,
      183,
      184,
      189,
      190,
      191,
      196,
      203,
      204,
      205,
      206,
      207,
      208,
      209,
      56,
      159,
      211,
      144,
      420,
      421,
      455,
      456,
      457,
      269,
      270,
      271,
      213,
      485,
      445,
      222,
      223,
      224,
      225,
      226,
      228,
      229,
      230,
      231,
      232,
      402,
      234,
      237,
      236,
      239,
      242,
      243,
      244,
      349,
      348,
      246,
      247,
      248,
      249,
      250,
      253,
      256,
      257,
      258,
      291,
      260,
      261,
      262,
      263,
      266,
      459,
      460,
      380,
      381,
      280,
      281,
      351,
      285,
      284,
      283,
      494,
      355,
      357,
      290,
      289,
      61,
      292,
      299,
      68,
      301,
      302,
      303,
      304,
      268,
      94,
      88,
      326,
      333,
      173,
      174,
      175,
      176,
      335,
      492,
      495,
      337,
      341,
      264,
      265,
      360,
      361,
      362,
      363,
      368,
      369,
      370,
      427,
      428,
      386,
      387,
      388,
      297,
      273,
      395,
      396,
      397,
      97,
      98,
      339,
      383,
      384,
      412,
      413,
      414,
      330,
      400,
      422,
      497,
      276,
      425,
      426,
      429,
      449,
      448,
      436,
      451,
      452,
      453,
      138,
      458,
      454,
      461,
      473,
      22,
      23,
      477,
      478,
      479,
      480,
      481,
      158,
      487,
      356
    ],
    "unique_colors": 301,
    "is_independent": true,
    "intervals": [
      {
        "vid": 600,
        "color": 194,
        "L": 1,
        "R": 3,
        "adj_key": [
          195,
          196
        ]
      },
      {
        "vid": 605,
        "color": 195,
        "L": 3,
        "R": 4,
        "adj_key": [
          196,
          197
        ]
      },
      {
        "vid": 6,
        "color": 2,
        "L": 8,
        "R": 9,
        "adj_key": [
          3,
          4
        ]
      },
      {
        "vid": 73,
        "color": 45,
        "L": 11,
        "R": 12,
        "adj_key": [
          46,
          47
        ]
      },
      {
        "vid": 22,
        "color": 12,
        "L": 15,
        "R": 17,
        "adj_key": [
          13,
          14
        ]
      },
      {
        "vid": 25,
        "color": 13,
        "L": 17,
        "R": 18,
        "adj_key": [
          14,
          15
        ]
      },
      {
        "vid": 27,
        "color": 14,
        "L": 18,
        "R": 19,
        "adj_key": [
          15,
          16
        ]
      },
      {
        "vid": 29,
        "color": 15,
        "L": 19,
        "R": 20,
        "adj_key": [
          16,
          17
        ]
      },
      {
        "vid": 30,
        "color": 16,
        "L": 20,
        "R": 21,
        "adj_key": [
          17,
          18
        ]
      },
      {
        "vid": 31,
        "color": 17,
        "L": 21,
        "R": 22,
        "adj_key": [
          18,
          19
        ]
      },
      {
        "vid": 32,
        "color": 18,
        "L": 22,
        "R": 23,
        "adj_key": [
          19,
          20
        ]
      },
      {
        "vid": 33,
        "color": 19,
        "L": 23,
        "R": 24,
        "adj_key": [
          20,
          21
        ]
      },
      {
        "vid": 41,
        "color": 26,
        "L": 27,
        "R": 28,
        "adj_key": [
          27,
          28
        ]
      },
      {
        "vid": 43,
        "color": 27,
        "L": 28,
        "R": 30,
        "adj_key": [
          28,
          29
        ]
      },
      {
        "vid": 45,
        "color": 28,
        "L": 30,
        "R": 31,
        "adj_key": [
          29,
          30
        ]
      },
      {
        "vid": 47,
        "color": 29,
        "L": 31,
        "R": 32,
        "adj_key": [
          30,
          31
        ]
      },
      {
        "vid": 49,
        "color": 30,
        "L": 32,
        "R": 33,
        "adj_key": [
          31,
          32
        ]
      },
      {
        "vid": 51,
        "color": 31,
        "L": 33,
        "R": 40,
        "adj_key": [
          32,
          33
        ]
      },
      {
        "vid": 54,
        "color": 32,
        "L": 40,
        "R": 42,
        "adj_key": [
          33,
          34
        ]
      },
      {
        "vid": 86,
        "color": 53,
        "L": 44,
        "R": 45,
        "adj_key": [
          54,
          55
        ]
      },
      {
        "vid": 105,
        "color": 64,
        "L": 55,
        "R": 56,
        "adj_key": [
          65,
          66
        ]
      },
      {
        "vid": 197,
        "color": 92,
        "L": 68,
        "R": 69,
        "adj_key": [
          93,
          94
        ]
      },
      {
        "vid": 1354,
        "color": 424,
        "L": 70,
        "R": 71,
        "adj_key": [
          425,
          426
        ]
      },
      {
        "vid": 102,
        "color": 58,
        "L": 74,
        "R": 75,
        "adj_key": [
          59,
          60
        ]
      },
      {
        "vid": 1235,
        "color": 372,
        "L": 77,
        "R": 84,
        "adj_key": [
          373,
          374
        ]
      },
      {
        "vid": 12,
        "color": 6,
        "L": 86,
        "R": 87,
        "adj_key": [
          7,
          8
        ]
      },
      {
        "vid": 11,
        "color": 5,
        "L": 87,
        "R": 88,
        "adj_key": [
          6,
          7
        ]
      },
      {
        "vid": 725,
        "color": 227,
        "L": 94,
        "R": 95,
        "adj_key": [
          228,
          229
        ]
      },
      {
        "vid": 78,
        "color": 49,
        "L": 100,
        "R": 101,
        "adj_key": [
          50,
          51
        ]
      },
      {
        "vid": 79,
        "color": 50,
        "L": 101,
        "R": 102,
        "adj_key": [
          51,
          52
        ]
      },
      {
        "vid": 1454,
        "color": 440,
        "L": 106,
        "R": 107,
        "adj_key": [
          441,
          442
        ]
      },
      {
        "vid": 1462,
        "color": 441,
        "L": 107,
        "R": 108,
        "adj_key": [
          442,
          443
        ]
      },
      {
        "vid": 744,
        "color": 235,
        "L": 112,
        "R": 113,
        "adj_key": [
          236,
          237
        ]
      },
      {
        "vid": 1198,
        "color": 359,
        "L": 114,
        "R": 116,
        "adj_key": [
          360,
          361
        ]
      },
      {
        "vid": 1537,
        "color": 463,
        "L": 125,
        "R": 127,
        "adj_key": [
          464,
          465
        ]
      },
      {
        "vid": 1548,
        "color": 464,
        "L": 127,
        "R": 128,
        "adj_key": [
          465,
          466
        ]
      },
      {
        "vid": 1552,
        "color": 465,
        "L": 128,
        "R": 129,
        "adj_key": [
          466,
          467
        ]
      },
      {
        "vid": 1556,
        "color": 466,
        "L": 129,
        "R": 130,
        "adj_key": [
          467,
          468
        ]
      },
      {
        "vid": 834,
        "color": 267,
        "L": 136,
        "R": 137,
        "adj_key": [
          268,
          269
        ]
      },
      {
        "vid": 1341,
        "color": 419,
        "L": 140,
        "R": 141,
        "adj_key": [
          420,
          421
        ]
      },
      {
        "vid": 62,
        "color": 40,
        "L": 146,
        "R": 147,
        "adj_key": [
          41,
          42
        ]
      },
      {
        "vid": 779,
        "color": 251,
        "L": 149,
        "R": 150,
        "adj_key": [
          252,
          253
        ]
      },
      {
        "vid": 782,
        "color": 252,
        "L": 150,
        "R": 151,
        "adj_key": [
          253,
          254
        ]
      },
      {
        "vid": 576,
        "color": 188,
        "L": 153,
        "R": 155,
        "adj_key": [
          189,
          190
        ]
      },
      {
        "vid": 788,
        "color": 254,
        "L": 157,
        "R": 158,
        "adj_key": [
          255,
          256
        ]
      },
      {
        "vid": 792,
        "color": 255,
        "L": 158,
        "R": 159,
        "adj_key": [
          256,
          257
        ]
      },
      {
        "vid": 129,
        "color": 66,
        "L": 162,
        "R": 163,
        "adj_key": [
          67,
          68
        ]
      },
      {
        "vid": 1413,
        "color": 434,
        "L": 164,
        "R": 165,
        "adj_key": [
          435,
          436
        ]
      },
      {
        "vid": 158,
        "color": 72,
        "L": 174,
        "R": 175,
        "adj_key": [
          73,
          74
        ]
      },
      {
        "vid": 160,
        "color": 73,
        "L": 175,
        "R": 176,
        "adj_key": [
          74,
          75
        ]
      },
      {
        "vid": 161,
        "color": 74,
        "L": 176,
        "R": 177,
        "adj_key": [
          75,
          76
        ]
      },
      {
        "vid": 162,
        "color": 75,
        "L": 177,
        "R": 178,
        "adj_key": [
          76,
          77
        ]
      },
      {
        "vid": 163,
        "color": 83,
        "L": 179,
        "R": 180,
        "adj_key": [
          84,
          85
        ]
      },
      {
        "vid": 164,
        "color": 84,
        "L": 180,
        "R": 181,
        "adj_key": [
          85,
          86
        ]
      },
      {
        "vid": 165,
        "color": 85,
        "L": 181,
        "R": 183,
        "adj_key": [
          86,
          87
        ]
      },
      {
        "vid": 166,
        "color": 86,
        "L": 183,
        "R": 184,
        "adj_key": [
          87,
          88
        ]
      },
      {
        "vid": 170,
        "color": 87,
        "L": 184,
        "R": 185,
        "adj_key": [
          88,
          89
        ]
      },
      {
        "vid": 212,
        "color": 93,
        "L": 186,
        "R": 187,
        "adj_key": [
          94,
          95
        ]
      },
      {
        "vid": 254,
        "color": 100,
        "L": 188,
        "R": 189,
        "adj_key": [
          101,
          102
        ]
      },
      {
        "vid": 258,
        "color": 101,
        "L": 189,
        "R": 190,
        "adj_key": [
          102,
          103
        ]
      },
      {
        "vid": 1434,
        "color": 437,
        "L": 191,
        "R": 192,
        "adj_key": [
          438,
          439
        ]
      },
      {
        "vid": 1440,
        "color": 438,
        "L": 192,
        "R": 194,
        "adj_key": [
          439,
          440
        ]
      },
      {
        "vid": 1447,
        "color": 439,
        "L": 194,
        "R": 195,
        "adj_key": [
          440,
          441
        ]
      },
      {
        "vid": 271,
        "color": 106,
        "L": 196,
        "R": 197,
        "adj_key": [
          107,
          108
        ]
      },
      {
        "vid": 120,
        "color": 65,
        "L": 207,
        "R": 210,
        "adj_key": [
          66,
          67
        ]
      },
      {
        "vid": 1242,
        "color": 374,
        "L": 214,
        "R": 215,
        "adj_key": [
          375,
          376
        ]
      },
      {
        "vid": 1248,
        "color": 375,
        "L": 215,
        "R": 216,
        "adj_key": [
          376,
          377
        ]
      },
      {
        "vid": 1255,
        "color": 376,
        "L": 216,
        "R": 217,
        "adj_key": [
          377,
          378
        ]
      },
      {
        "vid": 508,
        "color": 168,
        "L": 225,
        "R": 226,
        "adj_key": [
          169,
          170
        ]
      },
      {
        "vid": 1079,
        "color": 328,
        "L": 229,
        "R": 230,
        "adj_key": [
          329,
          330
        ]
      },
      {
        "vid": 284,
        "color": 107,
        "L": 231,
        "R": 251,
        "adj_key": [
          108,
          109
        ]
      },
      {
        "vid": 290,
        "color": 108,
        "L": 251,
        "R": 252,
        "adj_key": [
          109,
          110
        ]
      },
      {
        "vid": 294,
        "color": 109,
        "L": 252,
        "R": 253,
        "adj_key": [
          110,
          111
        ]
      },
      {
        "vid": 298,
        "color": 110,
        "L": 253,
        "R": 254,
        "adj_key": [
          111,
          112
        ]
      },
      {
        "vid": 323,
        "color": 113,
        "L": 256,
        "R": 257,
        "adj_key": [
          114,
          115
        ]
      },
      {
        "vid": 313,
        "color": 112,
        "L": 260,
        "R": 262,
        "adj_key": [
          113,
          114
        ]
      },
      {
        "vid": 141,
        "color": 67,
        "L": 269,
        "R": 271,
        "adj_key": [
          68,
          69
        ]
      },
      {
        "vid": 334,
        "color": 114,
        "L": 276,
        "R": 277,
        "adj_key": [
          115,
          116
        ]
      },
      {
        "vid": 337,
        "color": 115,
        "L": 277,
        "R": 284,
        "adj_key": [
          116,
          117
        ]
      },
      {
        "vid": 339,
        "color": 116,
        "L": 284,
        "R": 285,
        "adj_key": [
          117,
          118
        ]
      },
      {
        "vid": 341,
        "color": 117,
        "L": 285,
        "R": 286,
        "adj_key": [
          118,
          119
        ]
      },
      {
        "vid": 344,
        "color": 118,
        "L": 286,
        "R": 299,
        "adj_key": [
          119,
          120
        ]
      },
      {
        "vid": 349,
        "color": 119,
        "L": 299,
        "R": 301,
        "adj_key": [
          120,
          121
        ]
      },
      {
        "vid": 554,
        "color": 185,
        "L": 306,
        "R": 307,
        "adj_key": [
          186,
          187
        ]
      },
      {
        "vid": 560,
        "color": 186,
        "L": 307,
        "R": 309,
        "adj_key": [
          187,
          188
        ]
      },
      {
        "vid": 569,
        "color": 187,
        "L": 309,
        "R": 310,
        "adj_key": [
          188,
          189
        ]
      },
      {
        "vid": 355,
        "color": 120,
        "L": 313,
        "R": 314,
        "adj_key": [
          121,
          122
        ]
      },
      {
        "vid": 358,
        "color": 121,
        "L": 314,
        "R": 315,
        "adj_key": [
          122,
          123
        ]
      },
      {
        "vid": 360,
        "color": 122,
        "L": 315,
        "R": 317,
        "adj_key": [
          123,
          124
        ]
      },
      {
        "vid": 621,
        "color": 199,
        "L": 320,
        "R": 327,
        "adj_key": [
          200,
          201
        ]
      },
      {
        "vid": 626,
        "color": 200,
        "L": 327,
        "R": 328,
        "adj_key": [
          201,
          202
        ]
      },
      {
        "vid": 365,
        "color": 126,
        "L": 333,
        "R": 335,
        "adj_key": [
          127,
          128
        ]
      },
      {
        "vid": 367,
        "color": 129,
        "L": 336,
        "R": 337,
        "adj_key": [
          130,
          131
        ]
      },
      {
        "vid": 368,
        "color": 130,
        "L": 337,
        "R": 338,
        "adj_key": [
          131,
          132
        ]
      },
      {
        "vid": 369,
        "color": 131,
        "L": 338,
        "R": 339,
        "adj_key": [
          132,
          133
        ]
      },
      {
        "vid": 370,
        "color": 132,
        "L": 339,
        "R": 340,
        "adj_key": [
          133,
          134
        ]
      },
      {
        "vid": 371,
        "color": 133,
        "L": 340,
        "R": 341,
        "adj_key": [
          134,
          135
        ]
      },
      {
        "vid": 372,
        "color": 134,
        "L": 341,
        "R": 342,
        "adj_key": [
          135,
          136
        ]
      },
      {
        "vid": 1401,
        "color": 433,
        "L": 344,
        "R": 345,
        "adj_key": [
          434,
          435
        ]
      },
      {
        "vid": 374,
        "color": 136,
        "L": 349,
        "R": 350,
        "adj_key": [
          137,
          138
        ]
      },
      {
        "vid": 190,
        "color": 91,
        "L": 353,
        "R": 355,
        "adj_key": [
          92,
          93
        ]
      },
      {
        "vid": 405,
        "color": 149,
        "L": 356,
        "R": 357,
        "adj_key": [
          150,
          151
        ]
      },
      {
        "vid": 403,
        "color": 148,
        "L": 357,
        "R": 358,
        "adj_key": [
          149,
          150
        ]
      },
      {
        "vid": 401,
        "color": 147,
        "L": 358,
        "R": 360,
        "adj_key": [
          148,
          149
        ]
      },
      {
        "vid": 417,
        "color": 151,
        "L": 362,
        "R": 363,
        "adj_key": [
          152,
          153
        ]
      },
      {
        "vid": 425,
        "color": 152,
        "L": 363,
        "R": 364,
        "adj_key": [
          153,
          154
        ]
      },
      {
        "vid": 433,
        "color": 153,
        "L": 364,
        "R": 365,
        "adj_key": [
          154,
          155
        ]
      },
      {
        "vid": 440,
        "color": 154,
        "L": 365,
        "R": 366,
        "adj_key": [
          155,
          156
        ]
      },
      {
        "vid": 411,
        "color": 150,
        "L": 367,
        "R": 368,
        "adj_key": [
          151,
          152
        ]
      },
      {
        "vid": 449,
        "color": 155,
        "L": 372,
        "R": 373,
        "adj_key": [
          156,
          157
        ]
      },
      {
        "vid": 1041,
        "color": 305,
        "L": 385,
        "R": 386,
        "adj_key": [
          306,
          307
        ]
      },
      {
        "vid": 1045,
        "color": 306,
        "L": 386,
        "R": 387,
        "adj_key": [
          307,
          308
        ]
      },
      {
        "vid": 1048,
        "color": 307,
        "L": 387,
        "R": 388,
        "adj_key": [
          308,
          309
        ]
      },
      {
        "vid": 458,
        "color": 156,
        "L": 394,
        "R": 395,
        "adj_key": [
          157,
          158
        ]
      },
      {
        "vid": 1165,
        "color": 353,
        "L": 396,
        "R": 397,
        "adj_key": [
          354,
          355
        ]
      },
      {
        "vid": 1169,
        "color": 354,
        "L": 397,
        "R": 398,
        "adj_key": [
          355,
          356
        ]
      },
      {
        "vid": 973,
        "color": 287,
        "L": 399,
        "R": 406,
        "adj_key": [
          288,
          289
        ]
      },
      {
        "vid": 983,
        "color": 288,
        "L": 406,
        "R": 408,
        "adj_key": [
          289,
          290
        ]
      },
      {
        "vid": 1567,
        "color": 468,
        "L": 414,
        "R": 415,
        "adj_key": [
          469,
          470
        ]
      },
      {
        "vid": 1571,
        "color": 469,
        "L": 415,
        "R": 417,
        "adj_key": [
          470,
          471
        ]
      },
      {
        "vid": 485,
        "color": 162,
        "L": 420,
        "R": 421,
        "adj_key": [
          163,
          164
        ]
      },
      {
        "vid": 488,
        "color": 163,
        "L": 421,
        "R": 422,
        "adj_key": [
          164,
          165
        ]
      },
      {
        "vid": 183,
        "color": 90,
        "L": 424,
        "R": 425,
        "adj_key": [
          91,
          92
        ]
      },
      {
        "vid": 495,
        "color": 165,
        "L": 428,
        "R": 429,
        "adj_key": [
          166,
          167
        ]
      },
      {
        "vid": 498,
        "color": 166,
        "L": 429,
        "R": 436,
        "adj_key": [
          167,
          168
        ]
      },
      {
        "vid": 503,
        "color": 167,
        "L": 436,
        "R": 442,
        "adj_key": [
          168,
          169
        ]
      },
      {
        "vid": 514,
        "color": 169,
        "L": 443,
        "R": 444,
        "adj_key": [
          170,
          171
        ]
      },
      {
        "vid": 380,
        "color": 139,
        "L": 445,
        "R": 446,
        "adj_key": [
          140,
          141
        ]
      },
      {
        "vid": 383,
        "color": 140,
        "L": 446,
        "R": 447,
        "adj_key": [
          141,
          142
        ]
      },
      {
        "vid": 386,
        "color": 141,
        "L": 447,
        "R": 448,
        "adj_key": [
          142,
          143
        ]
      },
      {
        "vid": 20,
        "color": 11,
        "L": 451,
        "R": 459,
        "adj_key": [
          12,
          13
        ]
      },
      {
        "vid": 520,
        "color": 170,
        "L": 461,
        "R": 462,
        "adj_key": [
          171,
          172
        ]
      },
      {
        "vid": 1391,
        "color": 432,
        "L": 463,
        "R": 467,
        "adj_key": [
          433,
          434
        ]
      },
      {
        "vid": 917,
        "color": 274,
        "L": 478,
        "R": 479,
        "adj_key": [
          275,
          276
        ]
      },
      {
        "vid": 613,
        "color": 197,
        "L": 482,
        "R": 483,
        "adj_key": [
          198,
          199
        ]
      },
      {
        "vid": 618,
        "color": 198,
        "L": 483,
        "R": 484,
        "adj_key": [
          199,
          200
        ]
      },
      {
        "vid": 632,
        "color": 201,
        "L": 486,
        "R": 487,
        "adj_key": [
          202,
          203
        ]
      },
      {
        "vid": 1297,
        "color": 391,
        "L": 488,
        "R": 489,
        "adj_key": [
          392,
          393
        ]
      },
      {
        "vid": 756,
        "color": 238,
        "L": 490,
        "R": 491,
        "adj_key": [
          239,
          240
        ]
      },
      {
        "vid": 640,
        "color": 202,
        "L": 493,
        "R": 494,
        "adj_key": [
          203,
          204
        ]
      },
      {
        "vid": 539,
        "color": 178,
        "L": 495,
        "R": 496,
        "adj_key": [
          179,
          180
        ]
      },
      {
        "vid": 467,
        "color": 157,
        "L": 500,
        "R": 501,
        "adj_key": [
          158,
          159
        ]
      },
      {
        "vid": 541,
        "color": 180,
        "L": 503,
        "R": 504,
        "adj_key": [
          181,
          182
        ]
      },
      {
        "vid": 542,
        "color": 181,
        "L": 504,
        "R": 505,
        "adj_key": [
          182,
          183
        ]
      },
      {
        "vid": 543,
        "color": 182,
        "L": 505,
        "R": 506,
        "adj_key": [
          183,
          184
        ]
      },
      {
        "vid": 544,
        "color": 183,
        "L": 506,
        "R": 507,
        "adj_key": [
          184,
          185
        ]
      },
      {
        "vid": 549,
        "color": 184,
        "L": 507,
        "R": 508,
        "adj_key": [
          185,
          186
        ]
      },
      {
        "vid": 585,
        "color": 189,
        "L": 512,
        "R": 541,
        "adj_key": [
          190,
          191
        ]
      },
      {
        "vid": 590,
        "color": 190,
        "L": 541,
        "R": 542,
        "adj_key": [
          191,
          192
        ]
      },
      {
        "vid": 593,
        "color": 191,
        "L": 542,
        "R": 543,
        "adj_key": [
          192,
          193
        ]
      },
      {
        "vid": 611,
        "color": 196,
        "L": 548,
        "R": 552,
        "adj_key": [
          197,
          198
        ]
      },
      {
        "vid": 645,
        "color": 203,
        "L": 561,
        "R": 562,
        "adj_key": [
          204,
          205
        ]
      },
      {
        "vid": 650,
        "color": 204,
        "L": 562,
        "R": 563,
        "adj_key": [
          205,
          206
        ]
      },
      {
        "vid": 654,
        "color": 205,
        "L": 563,
        "R": 564,
        "adj_key": [
          206,
          207
        ]
      },
      {
        "vid": 656,
        "color": 206,
        "L": 564,
        "R": 565,
        "adj_key": [
          207,
          208
        ]
      },
      {
        "vid": 661,
        "color": 207,
        "L": 565,
        "R": 567,
        "adj_key": [
          208,
          209
        ]
      },
      {
        "vid": 666,
        "color": 208,
        "L": 567,
        "R": 569,
        "adj_key": [
          209,
          210
        ]
      },
      {
        "vid": 675,
        "color": 209,
        "L": 569,
        "R": 571,
        "adj_key": [
          210,
          211
        ]
      },
      {
        "vid": 96,
        "color": 56,
        "L": 574,
        "R": 578,
        "adj_key": [
          57,
          58
        ]
      },
      {
        "vid": 481,
        "color": 159,
        "L": 588,
        "R": 589,
        "adj_key": [
          160,
          161
        ]
      },
      {
        "vid": 685,
        "color": 211,
        "L": 594,
        "R": 595,
        "adj_key": [
          212,
          213
        ]
      },
      {
        "vid": 399,
        "color": 144,
        "L": 600,
        "R": 602,
        "adj_key": [
          145,
          146
        ]
      },
      {
        "vid": 1345,
        "color": 420,
        "L": 604,
        "R": 611,
        "adj_key": [
          421,
          422
        ]
      },
      {
        "vid": 1347,
        "color": 421,
        "L": 611,
        "R": 612,
        "adj_key": [
          422,
          423
        ]
      },
      {
        "vid": 1496,
        "color": 455,
        "L": 614,
        "R": 615,
        "adj_key": [
          456,
          457
        ]
      },
      {
        "vid": 1503,
        "color": 456,
        "L": 615,
        "R": 616,
        "adj_key": [
          457,
          458
        ]
      },
      {
        "vid": 1509,
        "color": 457,
        "L": 616,
        "R": 617,
        "adj_key": [
          458,
          459
        ]
      },
      {
        "vid": 855,
        "color": 269,
        "L": 620,
        "R": 621,
        "adj_key": [
          270,
          271
        ]
      },
      {
        "vid": 865,
        "color": 270,
        "L": 621,
        "R": 623,
        "adj_key": [
          271,
          272
        ]
      },
      {
        "vid": 881,
        "color": 271,
        "L": 623,
        "R": 633,
        "adj_key": [
          272,
          273
        ]
      },
      {
        "vid": 694,
        "color": 213,
        "L": 634,
        "R": 638,
        "adj_key": [
          214,
          215
        ]
      },
      {
        "vid": 1594,
        "color": 485,
        "L": 649,
        "R": 656,
        "adj_key": [
          486,
          487
        ]
      },
      {
        "vid": 1473,
        "color": 445,
        "L": 657,
        "R": 659,
        "adj_key": [
          446,
          447
        ]
      },
      {
        "vid": 708,
        "color": 222,
        "L": 663,
        "R": 664,
        "adj_key": [
          223,
          224
        ]
      },
      {
        "vid": 711,
        "color": 223,
        "L": 664,
        "R": 665,
        "adj_key": [
          224,
          225
        ]
      },
      {
        "vid": 714,
        "color": 224,
        "L": 665,
        "R": 666,
        "adj_key": [
          225,
          226
        ]
      },
      {
        "vid": 718,
        "color": 225,
        "L": 666,
        "R": 668,
        "adj_key": [
          226,
          227
        ]
      },
      {
        "vid": 723,
        "color": 226,
        "L": 668,
        "R": 669,
        "adj_key": [
          227,
          228
        ]
      },
      {
        "vid": 730,
        "color": 228,
        "L": 670,
        "R": 678,
        "adj_key": [
          229,
          230
        ]
      },
      {
        "vid": 733,
        "color": 229,
        "L": 678,
        "R": 679,
        "adj_key": [
          230,
          231
        ]
      },
      {
        "vid": 734,
        "color": 230,
        "L": 679,
        "R": 680,
        "adj_key": [
          231,
          232
        ]
      },
      {
        "vid": 735,
        "color": 231,
        "L": 680,
        "R": 681,
        "adj_key": [
          232,
          233
        ]
      },
      {
        "vid": 736,
        "color": 232,
        "L": 681,
        "R": 682,
        "adj_key": [
          233,
          234
        ]
      },
      {
        "vid": 1321,
        "color": 402,
        "L": 683,
        "R": 684,
        "adj_key": [
          403,
          404
        ]
      },
      {
        "vid": 740,
        "color": 234,
        "L": 688,
        "R": 689,
        "adj_key": [
          235,
          236
        ]
      },
      {
        "vid": 754,
        "color": 237,
        "L": 692,
        "R": 693,
        "adj_key": [
          238,
          239
        ]
      },
      {
        "vid": 751,
        "color": 236,
        "L": 703,
        "R": 711,
        "adj_key": [
          237,
          238
        ]
      },
      {
        "vid": 761,
        "color": 239,
        "L": 714,
        "R": 715,
        "adj_key": [
          240,
          241
        ]
      },
      {
        "vid": 762,
        "color": 242,
        "L": 716,
        "R": 717,
        "adj_key": [
          243,
          244
        ]
      },
      {
        "vid": 763,
        "color": 243,
        "L": 717,
        "R": 718,
        "adj_key": [
          244,
          245
        ]
      },
      {
        "vid": 764,
        "color": 244,
        "L": 718,
        "R": 719,
        "adj_key": [
          245,
          246
        ]
      },
      {
        "vid": 1151,
        "color": 349,
        "L": 723,
        "R": 724,
        "adj_key": [
          350,
          351
        ]
      },
      {
        "vid": 1146,
        "color": 348,
        "L": 724,
        "R": 725,
        "adj_key": [
          349,
          350
        ]
      },
      {
        "vid": 769,
        "color": 246,
        "L": 726,
        "R": 727,
        "adj_key": [
          247,
          248
        ]
      },
      {
        "vid": 771,
        "color": 247,
        "L": 727,
        "R": 728,
        "adj_key": [
          248,
          249
        ]
      },
      {
        "vid": 773,
        "color": 248,
        "L": 728,
        "R": 729,
        "adj_key": [
          249,
          250
        ]
      },
      {
        "vid": 775,
        "color": 249,
        "L": 729,
        "R": 730,
        "adj_key": [
          250,
          251
        ]
      },
      {
        "vid": 777,
        "color": 250,
        "L": 730,
        "R": 731,
        "adj_key": [
          251,
          252
        ]
      },
      {
        "vid": 786,
        "color": 253,
        "L": 733,
        "R": 734,
        "adj_key": [
          254,
          255
        ]
      },
      {
        "vid": 797,
        "color": 256,
        "L": 736,
        "R": 744,
        "adj_key": [
          257,
          258
        ]
      },
      {
        "vid": 801,
        "color": 257,
        "L": 744,
        "R": 745,
        "adj_key": [
          258,
          259
        ]
      },
      {
        "vid": 804,
        "color": 258,
        "L": 745,
        "R": 746,
        "adj_key": [
          259,
          260
        ]
      },
      {
        "vid": 1003,
        "color": 291,
        "L": 751,
        "R": 758,
        "adj_key": [
          292,
          293
        ]
      },
      {
        "vid": 810,
        "color": 260,
        "L": 759,
        "R": 760,
        "adj_key": [
          261,
          262
        ]
      },
      {
        "vid": 811,
        "color": 261,
        "L": 760,
        "R": 761,
        "adj_key": [
          262,
          263
        ]
      },
      {
        "vid": 812,
        "color": 262,
        "L": 761,
        "R": 762,
        "adj_key": [
          263,
          264
        ]
      },
      {
        "vid": 813,
        "color": 263,
        "L": 762,
        "R": 763,
        "adj_key": [
          264,
          265
        ]
      },
      {
        "vid": 829,
        "color": 266,
        "L": 765,
        "R": 766,
        "adj_key": [
          267,
          268
        ]
      },
      {
        "vid": 1517,
        "color": 459,
        "L": 769,
        "R": 770,
        "adj_key": [
          460,
          461
        ]
      },
      {
        "vid": 1521,
        "color": 460,
        "L": 770,
        "R": 771,
        "adj_key": [
          461,
          462
        ]
      },
      {
        "vid": 1262,
        "color": 380,
        "L": 777,
        "R": 778,
        "adj_key": [
          381,
          382
        ]
      },
      {
        "vid": 1263,
        "color": 381,
        "L": 778,
        "R": 779,
        "adj_key": [
          382,
          383
        ]
      },
      {
        "vid": 958,
        "color": 280,
        "L": 781,
        "R": 784,
        "adj_key": [
          281,
          282
        ]
      },
      {
        "vid": 959,
        "color": 281,
        "L": 784,
        "R": 785,
        "adj_key": [
          282,
          283
        ]
      },
      {
        "vid": 1161,
        "color": 351,
        "L": 786,
        "R": 787,
        "adj_key": [
          352,
          353
        ]
      },
      {
        "vid": 963,
        "color": 285,
        "L": 788,
        "R": 794,
        "adj_key": [
          286,
          287
        ]
      },
      {
        "vid": 962,
        "color": 284,
        "L": 794,
        "R": 795,
        "adj_key": [
          285,
          286
        ]
      },
      {
        "vid": 961,
        "color": 283,
        "L": 795,
        "R": 796,
        "adj_key": [
          284,
          285
        ]
      },
      {
        "vid": 1621,
        "color": 494,
        "L": 805,
        "R": 806,
        "adj_key": [
          495,
          496
        ]
      },
      {
        "vid": 1176,
        "color": 355,
        "L": 807,
        "R": 808,
        "adj_key": [
          356,
          357
        ]
      },
      {
        "vid": 1184,
        "color": 357,
        "L": 814,
        "R": 815,
        "adj_key": [
          358,
          359
        ]
      },
      {
        "vid": 999,
        "color": 290,
        "L": 817,
        "R": 818,
        "adj_key": [
          291,
          292
        ]
      },
      {
        "vid": 995,
        "color": 289,
        "L": 820,
        "R": 821,
        "adj_key": [
          290,
          291
        ]
      },
      {
        "vid": 104,
        "color": 61,
        "L": 823,
        "R": 824,
        "adj_key": [
          62,
          63
        ]
      },
      {
        "vid": 1011,
        "color": 292,
        "L": 833,
        "R": 839,
        "adj_key": [
          293,
          294
        ]
      },
      {
        "vid": 1026,
        "color": 299,
        "L": 842,
        "R": 854,
        "adj_key": [
          300,
          301
        ]
      },
      {
        "vid": 154,
        "color": 68,
        "L": 855,
        "R": 858,
        "adj_key": [
          69,
          70
        ]
      },
      {
        "vid": 1029,
        "color": 301,
        "L": 860,
        "R": 861,
        "adj_key": [
          302,
          303
        ]
      },
      {
        "vid": 1030,
        "color": 302,
        "L": 861,
        "R": 862,
        "adj_key": [
          303,
          304
        ]
      },
      {
        "vid": 1032,
        "color": 303,
        "L": 862,
        "R": 869,
        "adj_key": [
          304,
          305
        ]
      },
      {
        "vid": 1037,
        "color": 304,
        "L": 869,
        "R": 876,
        "adj_key": [
          305,
          306
        ]
      },
      {
        "vid": 847,
        "color": 268,
        "L": 887,
        "R": 888,
        "adj_key": [
          269,
          270
        ]
      },
      {
        "vid": 231,
        "color": 94,
        "L": 907,
        "R": 908,
        "adj_key": [
          95,
          96
        ]
      },
      {
        "vid": 177,
        "color": 88,
        "L": 920,
        "R": 974,
        "adj_key": [
          89,
          90
        ]
      },
      {
        "vid": 1067,
        "color": 326,
        "L": 985,
        "R": 986,
        "adj_key": [
          327,
          328
        ]
      },
      {
        "vid": 1116,
        "color": 333,
        "L": 987,
        "R": 988,
        "adj_key": [
          334,
          335
        ]
      },
      {
        "vid": 532,
        "color": 173,
        "L": 990,
        "R": 994,
        "adj_key": [
          174,
          175
        ]
      },
      {
        "vid": 535,
        "color": 174,
        "L": 995,
        "R": 996,
        "adj_key": [
          175,
          176
        ]
      },
      {
        "vid": 536,
        "color": 175,
        "L": 996,
        "R": 997,
        "adj_key": [
          176,
          177
        ]
      },
      {
        "vid": 537,
        "color": 176,
        "L": 997,
        "R": 998,
        "adj_key": [
          177,
          178
        ]
      },
      {
        "vid": 1127,
        "color": 335,
        "L": 999,
        "R": 1000,
        "adj_key": [
          336,
          337
        ]
      },
      {
        "vid": 1615,
        "color": 492,
        "L": 1001,
        "R": 1002,
        "adj_key": [
          493,
          494
        ]
      },
      {
        "vid": 1626,
        "color": 495,
        "L": 1004,
        "R": 1005,
        "adj_key": [
          496,
          497
        ]
      },
      {
        "vid": 1132,
        "color": 337,
        "L": 1007,
        "R": 1010,
        "adj_key": [
          338,
          339
        ]
      },
      {
        "vid": 1144,
        "color": 341,
        "L": 1017,
        "R": 1018,
        "adj_key": [
          342,
          343
        ]
      },
      {
        "vid": 818,
        "color": 264,
        "L": 1023,
        "R": 1024,
        "adj_key": [
          265,
          266
        ]
      },
      {
        "vid": 823,
        "color": 265,
        "L": 1024,
        "R": 1030,
        "adj_key": [
          266,
          267
        ]
      },
      {
        "vid": 1218,
        "color": 360,
        "L": 1037,
        "R": 1038,
        "adj_key": [
          361,
          362
        ]
      },
      {
        "vid": 1223,
        "color": 361,
        "L": 1038,
        "R": 1053,
        "adj_key": [
          362,
          363
        ]
      },
      {
        "vid": 1226,
        "color": 362,
        "L": 1053,
        "R": 1054,
        "adj_key": [
          363,
          364
        ]
      },
      {
        "vid": 1228,
        "color": 363,
        "L": 1054,
        "R": 1055,
        "adj_key": [
          364,
          365
        ]
      },
      {
        "vid": 1230,
        "color": 368,
        "L": 1062,
        "R": 1063,
        "adj_key": [
          369,
          370
        ]
      },
      {
        "vid": 1231,
        "color": 369,
        "L": 1063,
        "R": 1064,
        "adj_key": [
          370,
          371
        ]
      },
      {
        "vid": 1232,
        "color": 370,
        "L": 1064,
        "R": 1065,
        "adj_key": [
          371,
          372
        ]
      },
      {
        "vid": 1374,
        "color": 427,
        "L": 1066,
        "R": 1067,
        "adj_key": [
          428,
          429
        ]
      },
      {
        "vid": 1378,
        "color": 428,
        "L": 1067,
        "R": 1068,
        "adj_key": [
          429,
          430
        ]
      },
      {
        "vid": 1278,
        "color": 386,
        "L": 1107,
        "R": 1108,
        "adj_key": [
          387,
          388
        ]
      },
      {
        "vid": 1281,
        "color": 387,
        "L": 1108,
        "R": 1109,
        "adj_key": [
          388,
          389
        ]
      },
      {
        "vid": 1285,
        "color": 388,
        "L": 1109,
        "R": 1110,
        "adj_key": [
          389,
          390
        ]
      },
      {
        "vid": 1021,
        "color": 297,
        "L": 1117,
        "R": 1118,
        "adj_key": [
          298,
          299
        ]
      },
      {
        "vid": 915,
        "color": 273,
        "L": 1123,
        "R": 1125,
        "adj_key": [
          274,
          275
        ]
      },
      {
        "vid": 1299,
        "color": 395,
        "L": 1138,
        "R": 1139,
        "adj_key": [
          396,
          397
        ]
      },
      {
        "vid": 1300,
        "color": 396,
        "L": 1139,
        "R": 1140,
        "adj_key": [
          397,
          398
        ]
      },
      {
        "vid": 1301,
        "color": 397,
        "L": 1140,
        "R": 1141,
        "adj_key": [
          398,
          399
        ]
      },
      {
        "vid": 248,
        "color": 97,
        "L": 1143,
        "R": 1144,
        "adj_key": [
          98,
          99
        ]
      },
      {
        "vid": 249,
        "color": 98,
        "L": 1144,
        "R": 1145,
        "adj_key": [
          99,
          100
        ]
      },
      {
        "vid": 1137,
        "color": 339,
        "L": 1150,
        "R": 1151,
        "adj_key": [
          340,
          341
        ]
      },
      {
        "vid": 1268,
        "color": 383,
        "L": 1152,
        "R": 1155,
        "adj_key": [
          384,
          385
        ]
      },
      {
        "vid": 1271,
        "color": 384,
        "L": 1155,
        "R": 1156,
        "adj_key": [
          385,
          386
        ]
      },
      {
        "vid": 1330,
        "color": 412,
        "L": 1157,
        "R": 1158,
        "adj_key": [
          413,
          414
        ]
      },
      {
        "vid": 1331,
        "color": 413,
        "L": 1158,
        "R": 1159,
        "adj_key": [
          414,
          415
        ]
      },
      {
        "vid": 1332,
        "color": 414,
        "L": 1159,
        "R": 1160,
        "adj_key": [
          415,
          416
        ]
      },
      {
        "vid": 1094,
        "color": 330,
        "L": 1162,
        "R": 1163,
        "adj_key": [
          331,
          332
        ]
      },
      {
        "vid": 1304,
        "color": 400,
        "L": 1175,
        "R": 1176,
        "adj_key": [
          401,
          402
        ]
      },
      {
        "vid": 1351,
        "color": 422,
        "L": 1180,
        "R": 1182,
        "adj_key": [
          423,
          424
        ]
      },
      {
        "vid": 1633,
        "color": 497,
        "L": 1190,
        "R": 1191,
        "adj_key": [
          498,
          499
        ]
      },
      {
        "vid": 941,
        "color": 276,
        "L": 1203,
        "R": 1223,
        "adj_key": [
          277,
          278
        ]
      },
      {
        "vid": 1366,
        "color": 425,
        "L": 1227,
        "R": 1228,
        "adj_key": [
          426,
          427
        ]
      },
      {
        "vid": 1373,
        "color": 426,
        "L": 1230,
        "R": 1231,
        "adj_key": [
          427,
          428
        ]
      },
      {
        "vid": 1381,
        "color": 429,
        "L": 1233,
        "R": 1234,
        "adj_key": [
          430,
          431
        ]
      },
      {
        "vid": 1478,
        "color": 449,
        "L": 1235,
        "R": 1236,
        "adj_key": [
          450,
          451
        ]
      },
      {
        "vid": 1477,
        "color": 448,
        "L": 1236,
        "R": 1238,
        "adj_key": [
          449,
          450
        ]
      },
      {
        "vid": 1431,
        "color": 436,
        "L": 1239,
        "R": 1240,
        "adj_key": [
          437,
          438
        ]
      },
      {
        "vid": 1481,
        "color": 451,
        "L": 1241,
        "R": 1243,
        "adj_key": [
          452,
          453
        ]
      },
      {
        "vid": 1484,
        "color": 452,
        "L": 1243,
        "R": 1251,
        "adj_key": [
          453,
          454
        ]
      },
      {
        "vid": 1489,
        "color": 453,
        "L": 1251,
        "R": 1252,
        "adj_key": [
          454,
          455
        ]
      },
      {
        "vid": 378,
        "color": 138,
        "L": 1283,
        "R": 1284,
        "adj_key": [
          139,
          140
        ]
      },
      {
        "vid": 1514,
        "color": 458,
        "L": 1288,
        "R": 1289,
        "adj_key": [
          459,
          460
        ]
      },
      {
        "vid": 1494,
        "color": 454,
        "L": 1293,
        "R": 1303,
        "adj_key": [
          455,
          456
        ]
      },
      {
        "vid": 1527,
        "color": 461,
        "L": 1309,
        "R": 1311,
        "adj_key": [
          462,
          463
        ]
      },
      {
        "vid": 1577,
        "color": 473,
        "L": 1315,
        "R": 1316,
        "adj_key": [
          474,
          475
        ]
      },
      {
        "vid": 36,
        "color": 22,
        "L": 1328,
        "R": 1336,
        "adj_key": [
          23,
          24
        ]
      },
      {
        "vid": 39,
        "color": 23,
        "L": 1336,
        "R": 1343,
        "adj_key": [
          24,
          25
        ]
      },
      {
        "vid": 1587,
        "color": 477,
        "L": 1353,
        "R": 1354,
        "adj_key": [
          478,
          479
        ]
      },
      {
        "vid": 1588,
        "color": 478,
        "L": 1354,
        "R": 1355,
        "adj_key": [
          479,
          480
        ]
      },
      {
        "vid": 1589,
        "color": 479,
        "L": 1355,
        "R": 1356,
        "adj_key": [
          480,
          481
        ]
      },
      {
        "vid": 1590,
        "color": 480,
        "L": 1356,
        "R": 1357,
        "adj_key": [
          481,
          482
        ]
      },
      {
        "vid": 1592,
        "color": 481,
        "L": 1357,
        "R": 1359,
        "adj_key": [
          482,
          483
        ]
      },
      {
        "vid": 477,
        "color": 158,
        "L": 1361,
        "R": 1362,
        "adj_key": [
          159,
          160
        ]
      },
      {
        "vid": 1607,
        "color": 487,
        "L": 1364,
        "R": 1370,
        "adj_key": [
          488,
          489
        ]
      },
      {
        "vid": 1183,
        "color": 356,
        "L": 1381,
        "R": 1382,
        "adj_key": [
          357,
          358
        ]
      }
    ]
  },
  "instance_id": 7,
  "source_file": "datasets/unsigned/n500_m1_unsigned_tries10.txt",
  "len_A": 500,
  "len_B": 1391
}